CityOfBinds/__init__.py
CityOfBinds/_version.py
CityOfBinds/src/_configs/constants.py
CityOfBinds/src/_configs/defaults.py
CityOfBinds/src/_configs/maps.py
CityOfBinds/src/_configs/overrides.py
CityOfBinds/src/_configs/valid_input/__init__.py
CityOfBinds/src/_configs/valid_input/valid_slash_command_prefixes.py
CityOfBinds/src/_configs/valid_input/valid_slash_commands.py
CityOfBinds/src/_configs/valid_input/valid_trigger_keys.py
CityOfBinds/src/_configs/valid_input/valid_trigger_modifiers.py
CityOfBinds/src/bfs/bind_file_system.py
CityOfBinds/src/bfs/fixtures/changeling_binds.py
CityOfBinds/src/bfs/fixtures/combat_mode.py
CityOfBinds/src/bfs/fixtures/generic_bfs_fixture.py
CityOfBinds/src/bfs/fixtures/persistent_autos.py
CityOfBinds/src/bfs/fixtures/persistent_toggles.py
CityOfBinds/src/bfs/fixtures/random_binds.py
CityOfBinds/src/bfs/fixtures/random_rotating_bind.py
CityOfBinds/src/bfs/fixtures/random_walk.py
CityOfBinds/src/bfs/fixtures/rotating_bind.py
CityOfBinds/src/bfs/fixtures/rotating_move_bind.py
CityOfBinds/src/bfs/fixtures/sequence_bind.py
CityOfBinds/src/core/content_managers/graph/bind_file_graph.py
CityOfBinds/src/core/content_managers/templates/bind_file_template.py
CityOfBinds/src/core/content_managers/templates/bind_template.py
CityOfBinds/src/core/content_managers/utils/command_factory.py
CityOfBinds/src/core/content_managers/utils/commands_template.py
CityOfBinds/src/core/content_publisher/bfg_publisher.py
CityOfBinds/src/core/content_publisher/safe_install.py
CityOfBinds/src/core/game_content/bind_file/bind_file.py
CityOfBinds/src/core/game_content/bind_file/comments/comment.py
CityOfBinds/src/core/game_content/bind_file/comments/comment_banner.py
CityOfBinds/src/core/game_content/binds/bind.py
CityOfBinds/src/core/game_content/binds/move_binds/move_bind.py
CityOfBinds/src/core/game_content/binds/move_binds/wasd_bind.py
CityOfBinds/src/core/game_content/command_group/command_group.py
cityofbinds-0.5.9.dist-info/licenses/LICENSE
cityofbinds-0.5.9.dist-info/METADATA
cityofbinds-0.5.9.dist-info/WHEEL
cityofbinds-0.5.9.dist-info/top_level.txt
cityofbinds-0.5.9.dist-info/RECORD
