Metadata-Version: 2.4
Name: CityOfBinds
Version: 0.5.9
Summary: Library to help create City of Heroes binds as simple or advanced as you'd like.
Author-email: brandon wade <bwade.dev@gmail.com>
License: MIT
Project-URL: Homepage, https://github.com/mockmoniker/city-of-binds
Project-URL: Bug Reports, https://github.com/mockmoniker/city-of-binds/issues
Project-URL: Source, https://github.com/mockmoniker/city-of-binds
Keywords: coh,city of heroes,gaming,keybinds,binds,automation
Classifier: Development Status :: 4 - Beta
Classifier: License :: OSI Approved :: MIT License
Classifier: Programming Language :: Python :: 3
Classifier: Programming Language :: Python :: 3.9
Classifier: Programming Language :: Python :: 3.10
Classifier: Programming Language :: Python :: 3.11
Classifier: Programming Language :: Python :: 3.12
Classifier: Programming Language :: Python :: 3.13
Classifier: Intended Audience :: Developers
Classifier: Topic :: Games/Entertainment
Classifier: Topic :: Software Development :: Code Generators
Requires-Python: >=3.9
License-File: LICENSE
Requires-Dist: networkx
Provides-Extra: dev
Requires-Dist: black[d]; extra == "dev"
Requires-Dist: pytest; extra == "dev"
Requires-Dist: isort; extra == "dev"
Requires-Dist: mypy; extra == "dev"
Requires-Dist: sphinx; extra == "dev"
Requires-Dist: sphinx-rtd-theme; extra == "dev"
Requires-Dist: build; extra == "dev"
Requires-Dist: twine; extra == "dev"
Dynamic: license-file
